predict_test_06/__init__.py
predict_test_v7-0.1.0.dist-info/LICENSE
predict_test_v7-0.1.0.dist-info/METADATA
predict_test_v7-0.1.0.dist-info/WHEEL
predict_test_v7-0.1.0.dist-info/top_level.txt
predict_test_v7-0.1.0.dist-info/RECORD
